MANIFEST.in
README.md
setup.py
dash_themes/__init__.py
dash_themes/base.css
dash_themes/bundle.js
dash_themes/bundle.js.map
dash_themes/editor.css
dash_themes/gallery.py
dash_themes/metadata.json
dash_themes/normalize.css
dash_themes/override-base.css
dash_themes/override-react-dates@12.3.0.css
dash_themes/override-react-select@1.0.0-rc.3.css
dash_themes/override-react-virtualized-select@3.1.0.css
dash_themes/rc-slider@6.1.2.css
dash_themes/react-dates@12.3.0.css
dash_themes/react-select@1.0.0-rc.3.css
dash_themes/react-virtualized-select@3.1.0.css
dash_themes/react-virtualized@9.9.0.css
dash_themes/var-base.css
dash_themes/var-rc-slider@6.1.2.css
dash_themes/var-react-dates@12.3.0.css
dash_themes/var-react-select@1.0.0-rc.3.css
dash_themes/var-react-virtualized-select@3.1.0.css
dash_themes/var-react-virtualized@9.9.0.css
dash_themes/version.py
dash_themes.egg-info/PKG-INFO
dash_themes.egg-info/SOURCES.txt
dash_themes.egg-info/dependency_links.txt
dash_themes.egg-info/top_level.txt