Metadata-Version: 1.0
Name: dash-themes
Version: 0.0.2
Summary: Dash UI component suite
Home-page: UNKNOWN
Author: plotly
Author-email: UNKNOWN
License: Commercial
Platform: UNKNOWN
